remote_kit/__init__.py
remote_kit-1.0.dist-info/LICENSE
remote_kit-1.0.dist-info/METADATA
remote_kit-1.0.dist-info/WHEEL
remote_kit-1.0.dist-info/top_level.txt
remote_kit-1.0.dist-info/RECORD
