Metadata-Version: 2.1
Name: remote-kit
Version: 1.0
Summary: Remote Kit is a Python library
Home-page: https://github.com/Ankit404butfound/Test_package
Author: Ankit Raj Mahapatra
Author-email: ankitrajjitendra816@gmail.com
License: MIT
Keywords: hello
Platform: UNKNOWN
Classifier: Development Status :: 3 - Alpha
Classifier: Intended Audience :: Developers
Classifier: Topic :: Software Development :: Build Tools
Classifier: License :: OSI Approved :: MIT License
Classifier: Programming Language :: Python :: 3
Classifier: Programming Language :: Python :: 3.4
Classifier: Programming Language :: Python :: 3.5
Classifier: Programming Language :: Python :: 3.6
Requires-Dist: Flask
